tcxreader/__init__.py
tcxreader/tcx_author.py
tcxreader/tcx_exercise.py
tcxreader/tcx_lap.py
tcxreader/tcx_track_point.py
tcxreader/tcxreader.py
tcxreader-0.4.8.dist-info/LICENSE
tcxreader-0.4.8.dist-info/METADATA
tcxreader-0.4.8.dist-info/WHEEL
tcxreader-0.4.8.dist-info/RECORD
