Metadata-Version: 2.1
Name: tcxreader
Version: 0.4.8
Summary: tcxreader is a reader for Garmin’s TCX file format. It also works well with missing data!
Home-page: https://github.com/alenrajsp/tcxreader
License: MIT
Author: Alen Rajšp
Author-email: alen.rajsp@gmail.com
Requires-Python: >=3.6,<4.0
Classifier: Development Status :: 4 - Beta
Classifier: License :: OSI Approved :: MIT License
Classifier: Operating System :: OS Independent
Classifier: Programming Language :: Python :: 3
Classifier: Programming Language :: Python :: 3.6
Classifier: Programming Language :: Python :: 3.7
Classifier: Programming Language :: Python :: 3.8
Classifier: Programming Language :: Python :: 3.9
Classifier: Programming Language :: Python :: 3.10
Classifier: Programming Language :: Python :: 3.11
Project-URL: Repository, https://github.com/alenrajsp/tcxreader
